getlooks/Makefile
getlooks/__init__.py
getlooks/cli.py
getlooks/core.py
getlooks/looks.py
getlooks/looks_path.py
getlooks/requirements.txt
getlooks/utils.py
gnomelooks-0.3.0.dist-info/METADATA
gnomelooks-0.3.0.dist-info/WHEEL
gnomelooks-0.3.0.dist-info/entry_points.txt
gnomelooks-0.3.0.dist-info/licenses/LICENSE
gnomelooks-0.3.0.dist-info/RECORD
