Metadata-Version: 2.4
Name: gnomelooks
Version: 0.3.0
Summary: 
License-File: LICENSE
Author: Rishang
Author-email: rishangbhavsarcs@gmail.com
Requires-Python: >=3.10,<4.0
Classifier: Programming Language :: Python :: 3
Classifier: Programming Language :: Python :: 3.10
Classifier: Programming Language :: Python :: 3.11
Classifier: Programming Language :: Python :: 3.12
Classifier: Programming Language :: Python :: 3.13
Classifier: Programming Language :: Python :: 3.14
Requires-Dist: beautifulsoup4
Requires-Dist: colorama
Requires-Dist: lxml
Requires-Dist: requests
Requires-Dist: rich (>=12.4.0)
Requires-Dist: typer (>=0.7.0)
